odoo10_addon_user_threshold-10.0.1.0.1-py2.7-nspkg.pth
odoo/addons/user_threshold/README.rst
odoo/addons/user_threshold/__init__.py
odoo/addons/user_threshold/__manifest__.py
odoo/addons/user_threshold/data/ir_config_parameter_data.xml
odoo/addons/user_threshold/data/user_threshold_data.xml
odoo/addons/user_threshold/i18n/ar.po
odoo/addons/user_threshold/i18n/ca.po
odoo/addons/user_threshold/i18n/da.po
odoo/addons/user_threshold/i18n/de.po
odoo/addons/user_threshold/i18n/el_GR.po
odoo/addons/user_threshold/i18n/es.po
odoo/addons/user_threshold/i18n/es_ES.po
odoo/addons/user_threshold/i18n/fi.po
odoo/addons/user_threshold/i18n/fr.po
odoo/addons/user_threshold/i18n/fr_CH.po
odoo/addons/user_threshold/i18n/fr_FR.po
odoo/addons/user_threshold/i18n/hr.po
odoo/addons/user_threshold/i18n/hr_HR.po
odoo/addons/user_threshold/i18n/it.po
odoo/addons/user_threshold/i18n/nl.po
odoo/addons/user_threshold/i18n/nl_NL.po
odoo/addons/user_threshold/i18n/pt.po
odoo/addons/user_threshold/i18n/pt_BR.po
odoo/addons/user_threshold/i18n/ro.po
odoo/addons/user_threshold/i18n/sl.po
odoo/addons/user_threshold/i18n/tr.po
odoo/addons/user_threshold/i18n/tr_TR.po
odoo/addons/user_threshold/i18n/zh_CN.po
odoo/addons/user_threshold/models/__init__.py
odoo/addons/user_threshold/models/ir_config_parameter.py
odoo/addons/user_threshold/models/res_company.py
odoo/addons/user_threshold/models/res_groups.py
odoo/addons/user_threshold/models/res_users.py
odoo/addons/user_threshold/tests/__init__.py
odoo/addons/user_threshold/tests/common.py
odoo/addons/user_threshold/tests/test_ir_config_parameter.py
odoo/addons/user_threshold/tests/test_res_company.py
odoo/addons/user_threshold/tests/test_res_groups.py
odoo/addons/user_threshold/tests/test_res_users.py
odoo/addons/user_threshold/views/res_company_view.xml
odoo/addons/user_threshold/views/res_users_view.xml
odoo10_addon_user_threshold-10.0.1.0.1.dist-info/DESCRIPTION.rst
odoo10_addon_user_threshold-10.0.1.0.1.dist-info/METADATA
odoo10_addon_user_threshold-10.0.1.0.1.dist-info/RECORD
odoo10_addon_user_threshold-10.0.1.0.1.dist-info/WHEEL
odoo10_addon_user_threshold-10.0.1.0.1.dist-info/metadata.json
odoo10_addon_user_threshold-10.0.1.0.1.dist-info/namespace_packages.txt
odoo10_addon_user_threshold-10.0.1.0.1.dist-info/top_level.txt
