Metadata-Version: 2.0
Name: odoo10-addon-user-threshold
Version: 10.0.1.0.1
Summary: Add Configurable User Threshold Support
Home-page: https://www.laslabs.com
Author: LasLabs, Odoo Community Association (OCA)
Author-email: support@odoo-community.org
License: LGPL-3
Platform: UNKNOWN
Classifier: Programming Language :: Python :: 2.7
Classifier: Framework :: Odoo
Classifier: License :: OSI Approved :: GNU Lesser General Public License v3 (LGPLv3)
Requires-Dist: odoo (<10.1dev,>=10.0)
